sogou_tr_async/__init__.py
sogou_tr_async/get_snuid.py
sogou_tr_async/sogou_tr_async.py
sogou_tr_async_free-0.0.23.dist-info/LICENSE
sogou_tr_async_free-0.0.23.dist-info/METADATA
sogou_tr_async_free-0.0.23.dist-info/WHEEL
sogou_tr_async_free-0.0.23.dist-info/top_level.txt
sogou_tr_async_free-0.0.23.dist-info/RECORD
