Metadata-Version: 2.1
Name: sogou-tr-async-free
Version: 0.0.23
Summary: sogou translate for free with async and proxy support
Home-page: http://github.com/ffreemt/sogou-tr-async-free
Author: mikeee
License: MIT License
Download-URL: https://github.com/ffreemt/sogou-tr-async-free/archive/v_0023.tar.gz
Keywords: machine translation,free,async
Platform: UNKNOWN
Classifier: Development Status :: 3 - Alpha
Classifier: Intended Audience :: Developers
Classifier: Programming Language :: Python :: 3
Classifier: Programming Language :: Python :: 3.6
Classifier: License :: OSI Approved :: MIT License
Requires-Dist: httpx
Requires-Dist: loguru
Requires-Dist: fuzzywuzzy
Requires-Dist: freemt-utils
